AsyncGraphqlZhongwenWendang/README.md
AsyncGraphqlZhongwenWendang/__init__.py
AsyncGraphqlZhongwenWendang/__main__.py
AsyncGraphqlZhongwenWendang/file.epub
AsyncGraphqlZhongwenWendang/index.html
AsyncGraphqlZhongwenWendang/css/__init__.py
AsyncGraphqlZhongwenWendang/css/annotations.css
AsyncGraphqlZhongwenWendang/css/main.css
AsyncGraphqlZhongwenWendang/css/normalize.css
AsyncGraphqlZhongwenWendang/css/popup.css
AsyncGraphqlZhongwenWendang/font/__init__.py
AsyncGraphqlZhongwenWendang/font/fontello.eot
AsyncGraphqlZhongwenWendang/font/fontello.svg
AsyncGraphqlZhongwenWendang/font/fontello.ttf
AsyncGraphqlZhongwenWendang/font/fontello.woff
AsyncGraphqlZhongwenWendang/img/__init__.py
AsyncGraphqlZhongwenWendang/img/annotator-glyph-sprite.png
AsyncGraphqlZhongwenWendang/img/annotator-icon-sprite.png
AsyncGraphqlZhongwenWendang/img/apple-touch-icon.png
AsyncGraphqlZhongwenWendang/img/cancelfullscreen.png
AsyncGraphqlZhongwenWendang/img/close.png
AsyncGraphqlZhongwenWendang/img/fullscreen.png
AsyncGraphqlZhongwenWendang/img/loader.gif
AsyncGraphqlZhongwenWendang/img/menu-icon.png
AsyncGraphqlZhongwenWendang/img/save.png
AsyncGraphqlZhongwenWendang/img/saved.png
AsyncGraphqlZhongwenWendang/img/settings-s.png
AsyncGraphqlZhongwenWendang/img/settings.png
AsyncGraphqlZhongwenWendang/img/star.png
AsyncGraphqlZhongwenWendang/js/__init__.py
AsyncGraphqlZhongwenWendang/js/epub.js
AsyncGraphqlZhongwenWendang/js/epub.min.js
AsyncGraphqlZhongwenWendang/js/epub.min.map
AsyncGraphqlZhongwenWendang/js/hooks.min.js
AsyncGraphqlZhongwenWendang/js/hooks.min.map
AsyncGraphqlZhongwenWendang/js/reader.js
AsyncGraphqlZhongwenWendang/js/reader.js.map
AsyncGraphqlZhongwenWendang/js/reader.min.js
AsyncGraphqlZhongwenWendang/js/reader.min.map
AsyncGraphqlZhongwenWendang/js/hooks/__init__.py
AsyncGraphqlZhongwenWendang/js/hooks/extensions/__init__.py
AsyncGraphqlZhongwenWendang/js/hooks/extensions/highlight.js
AsyncGraphqlZhongwenWendang/js/libs/__init__.py
async_graphql_zhongwen_wendang-2024.3.5.0.dist-info/METADATA
async_graphql_zhongwen_wendang-2024.3.5.0.dist-info/WHEEL
async_graphql_zhongwen_wendang-2024.3.5.0.dist-info/entry_points.txt
async_graphql_zhongwen_wendang-2024.3.5.0.dist-info/top_level.txt
async_graphql_zhongwen_wendang-2024.3.5.0.dist-info/RECORD
